google_ads_reports/__init__.py
google_ads_reports/client.py
google_ads_reports/exceptions.py
google_ads_reports/models.py
google_ads_reports/py.typed
google_ads_reports/retry.py
google_ads_reports/utils.py
google_ads_reports-2.0.2.dist-info/LICENSE
google_ads_reports-2.0.2.dist-info/METADATA
google_ads_reports-2.0.2.dist-info/WHEEL
google_ads_reports-2.0.2.dist-info/RECORD
