Metadata-Version: 2.3
Name: google-ads-reports
Version: 2.0.2
Summary: Simple Google Ads API client with automatic retries, exception handling, and flexible report generation
License: MIT
Keywords: google-ads,etl,data-extraction,reports,serverless
Author: Joao Brito
Requires-Python: >=3.11,<3.14
Classifier: Development Status :: 5 - Production/Stable
Classifier: Intended Audience :: Developers
Classifier: Intended Audience :: Information Technology
Classifier: License :: OSI Approved :: MIT License
Classifier: Operating System :: OS Independent
Classifier: Programming Language :: Python :: 3
Classifier: Programming Language :: Python :: 3.12
Classifier: Programming Language :: Python :: 3.13
Classifier: Programming Language :: Python :: 3.14
Classifier: Topic :: Software Development :: Libraries :: Python Modules
Classifier: Topic :: Internet :: WWW/HTTP :: Dynamic Content
Classifier: Typing :: Typed
Provides-Extra: dev
Requires-Dist: PyYAML (>=6.0.0)
Requires-Dist: google-ads (>=26.0.0,<29.0.0)
Requires-Dist: mypy (>=1.0.0) ; extra == "dev"
Requires-Dist: pytest (>=8.0.0) ; extra == "dev"
Requires-Dist: python-dotenv (>=1.0.0)
Requires-Dist: tqdm (>=4.65.0)
Requires-Dist: types-PyYAML (>=6.0.12.20240311) ; extra == "dev"
Requires-Dist: types-protobuf (>=4.24.0.20240417) ; extra == "dev"
Project-URL: Documentation, https://github.com/machado000/google-ads-reports#readme
Project-URL: Homepage, https://github.com/machado000/google-ads-reports
Project-URL: Issues, https://github.com/machado000/google-ads-reports/issues
